MANIFEST.in
README.rst
setup.py
examples/http-plain.conf
examples/http-trivial.conf
examples/nginx.conf
examples/trivial-and-pam.conf
examples/uwsgi.conf
omni/META
omni/__init__.py
omni/app.py
omni/cli.py
omni/httpserver.py
omni/log.py
omni/metadata.py
omni/store.py
omni/valid.py
omni.egg-info/PKG-INFO
omni.egg-info/SOURCES.txt
omni.egg-info/dependency_links.txt
omni.egg-info/entry_points.txt
omni.egg-info/requires.txt
omni.egg-info/top_level.txt
omni/stores/__init__.py
omni/stores/pam.py
omni/stores/plain.py
omni/stores/trivial.py
omni/test/__init__.py
omni/test/test_plain_store.py
omni/test/test_store.py
omni/test/test_web_routing.py
omni/web/__init__.py
omni/web/routing.py
omni/web/assets/html5-3.6-respond-1.1.0.min.js
omni/web/assets/normalize.css
omni/web/assets/normalize.min.css
omni/web/assets/omni-header-logo.png
omni/web/assets/styles.css
omni/web/templates/changepassword.mustache
omni/web/templates/master.mustache