Metadata-Version: 1.1
Name: omni
Version: 0.0.2
Summary: Omniscient Multiple Networked Identification
Home-page: https://github.com/aperezdc/omni
Author: Adrián Pérez de Castro
Author-email: aperez@igalia.com
License: GPLv3
Platform: UNKNOWN
Classifier: Development Status :: 4 - Beta
Classifier: Intended Audience :: Developers
Classifier: Natural Language :: English
Classifier: License :: OSI Approved :: GNU General Public License v3 (GPLv3)
Classifier: Programming Language :: Python :: 2.7
Classifier: Programming Language :: Python :: 3.4
Classifier: Programming Language :: Python
Classifier: Operating System :: OS Independent
